kiwiutils/finite_valued.py
kiwiutils/kiwilib.py
kiwiutils-0.1.1.dist-info/METADATA
kiwiutils-0.1.1.dist-info/WHEEL
kiwiutils-0.1.1.dist-info/RECORD
